jx_logger/__init__.py
jx_logger/core.py
jx_logger/formatters.py
jx_logger/handlers.py
jx_logger/utils.py
jx_logger-1.0.0.dist-info/licenses/LICENSE
jx_logger-1.0.0.dist-info/METADATA
jx_logger-1.0.0.dist-info/WHEEL
jx_logger-1.0.0.dist-info/top_level.txt
jx_logger-1.0.0.dist-info/RECORD
