Metadata-Version: 2.4
Name: jx-logger
Version: 1.0.0
Summary: Modern, high-performance Python logger for Python 3.11+
Author-email: JXGC Coding <jxgc.coding@gmail.com>
License: MIT
Project-URL: Homepage, https://github.com/jxgc-coding/jx_logger
Project-URL: Documentation, https://github.com/jxgc-coding/jx_logger#readme
Project-URL: Repository, https://github.com/jxgc-coding/jx_logger.git
Project-URL: Bug Tracker, https://github.com/jxgc-coding/jx_logger/issues
Project-URL: Changelog, https://github.com/jxgc-coding/jx_logger/blob/main/CHANGELOG.md
Keywords: logging,async,rich,json,monitoring,python311
Classifier: Development Status :: 4 - Beta
Classifier: Intended Audience :: Developers
Classifier: License :: OSI Approved :: MIT License
Classifier: Operating System :: OS Independent
Classifier: Programming Language :: Python :: 3
Classifier: Programming Language :: Python :: 3.11
Classifier: Programming Language :: Python :: 3.12
Classifier: Programming Language :: Python :: 3.13
Classifier: Topic :: Software Development :: Libraries :: Python Modules
Classifier: Topic :: System :: Logging
Classifier: Framework :: AsyncIO
Requires-Python: >=3.11
License-File: LICENSE
Requires-Dist: rich>=13.0.0
Requires-Dist: aiofiles>=23.0.0
Requires-Dist: structlog>=23.0.0
Provides-Extra: dev
Requires-Dist: pytest>=7.4.0; extra == "dev"
Requires-Dist: pytest-asyncio>=0.21.0; extra == "dev"
Requires-Dist: pytest-cov>=4.1.0; extra == "dev"
Requires-Dist: black>=23.0.0; extra == "dev"
Requires-Dist: ruff>=0.1.0; extra == "dev"
Requires-Dist: mypy>=1.5.0; extra == "dev"
Provides-Extra: testing
Requires-Dist: pytest>=7.4.0; extra == "testing"
Requires-Dist: pytest-asyncio>=0.21.0; extra == "testing"
Requires-Dist: pytest-cov>=4.1.0; extra == "testing"
Provides-Extra: performance
Requires-Dist: uvloop>=0.19.0; sys_platform != "win32" and extra == "performance"
Requires-Dist: orjson>=3.9.0; extra == "performance"
Dynamic: license-file
